{
  "transactions": [
    {
      "id": 1,
      "description": "Desenvolvimento de site",
      "type": "income",
      "category": "Venda",
      "price": 14000,
      "createdAt": "2023-04-26T17:48:20.409Z"
    },
    {
      "id": 2,
      "description": "Hamburger",
      "type": "outcome",
      "category": "Alimentação",
      "price": 50,
      "createdAt": "2023-04-26T17:37:20.409Z"
    },
    {
      "id": 3,
      "description": "Ignite Rocketseat",
      "type": "outcome",
      "category": "Educação",
      "price": 1980,
      "createdAt": "2023-04-26T17:22:20.409Z"
    },
    {
      "description": "Desenvolvimento de App",
      "category": "Venda",
      "price": 5000,
      "type": "income",
      "createdAt": "2023-04-28T16:48:53.037Z",
      "id": 4
    },
    {
      "description": "Pastel",
      "category": "Alimentação",
      "price": 5,
      "type": "outcome",
      "createdAt": "2023-05-02T12:53:53.554Z",
      "id": 5
    },
    {
      "description": "Poke",
      "category": "Alimentação",
      "price": 5,
      "type": "outcome",
      "createdAt": "2023-05-02T13:10:51.484Z",
      "id": 6
    },
    {
      "description": "Aluguel",
      "category": "Casa",
      "price": 1300,
      "type": "outcome",
      "createdAt": "2023-05-02T13:25:02.728Z",
      "id": 7
    }
  ]
}